mysync/__init__.py
mysync/sync_data.py
mysync/version.py
mysync/consumer/__init__.py
mysync/consumer/es_consumer.py
mysync/pipeline/__init__.py
mysync/pipeline/field_mapping_pipeline.py
mysync/producer/__init__.py
mysync/producer/mysql_producer.py
mysync/util/__init__.py
mysync/util/collection_util.py
mysync/util/config_util.py
mysync/util/default_config.yml
mysync/util/es_util.py
mysync/util/json_encoder.py
mysync/util/logger.py
mysync/util/method_util.py
mysync/util/sync_util.py
mysync/util/time_util.py
MySync-0.0.13.dist-info/METADATA
MySync-0.0.13.dist-info/WHEEL
MySync-0.0.13.dist-info/entry_points.txt
MySync-0.0.13.dist-info/top_level.txt
MySync-0.0.13.dist-info/zip-safe
MySync-0.0.13.dist-info/RECORD
