Metadata-Version: 2.1
Name: MySync
Version: 0.0.13
Summary: 同步MySQL数据到ElasticSearch
Home-page: https://github.com/mouday/MySync
Author: Peng Shiyu
Author-email: pengshiyuyx@gmail.com
License: MIT
Keywords: mysql elasticsearch
Platform: UNKNOWN
Classifier: Programming Language :: Python :: 3.7
Requires-Dist: PyYAML (==5.3)
Requires-Dist: elasticsearch (==5.3.0)
Requires-Dist: myquery (>=0.0.3)
